RLS/RLS.py
RLS/__init__.py
RLS_OF-1.11.dist-info/LICENSE.txt
RLS_OF-1.11.dist-info/METADATA
RLS_OF-1.11.dist-info/WHEEL
RLS_OF-1.11.dist-info/top_level.txt
RLS_OF-1.11.dist-info/RECORD
