Metadata-Version: 2.1
Name: RLS-OF
Version: 1.11
Summary: Regularised least squares objective function solver
Home-page: https://github.com/Joel-H-dot/RLS
Author: Joel Hampton
Author-email: joelelihampton@outlook.com
License: MIT
Keywords: non_linear optimisation RLS
Platform: UNKNOWN
Classifier: Development Status :: 4 - Beta
Classifier: Intended Audience :: Science/Research 
Classifier: License :: OSI Approved :: MIT License
Classifier: Programming Language :: Python :: 3
Requires-Dist: numpy
Requires-Dist: TRA
